.clang-format
.flake8
.gitignore
.gitmodules
CHANGELOG.md
CODEOWNERS
CODE_OF_CONDUCT
Dockerfile
Dockerfile-cuda
Dockerfile-embedded
LICENSE
MANIFEST.in
Makefile
README.md
__init__.py
description.txt
packages.txt
setup.py
./src/opendr/__init__.py
./src/opendr/_setup.py
./src/opendr/_version.py
./src/opendr/control/__init__.py
./src/opendr/engine/__init__.py
./src/opendr/engine/constants.py
./src/opendr/engine/data.py
./src/opendr/engine/datasets.py
./src/opendr/engine/example_learner.py
./src/opendr/engine/learners.py
./src/opendr/engine/target.py
./src/opendr/perception/__init__.py
./src/opendr/perception/pose_estimation/__init__.py
./src/opendr/perception/pose_estimation/dependencies.ini
./src/opendr/perception/pose_estimation/hr_pose_estimation/README.md
./src/opendr/perception/pose_estimation/hr_pose_estimation/__init__.py
./src/opendr/perception/pose_estimation/hr_pose_estimation/high_resolution_learner.py
./src/opendr/perception/pose_estimation/lightweight_open_pose/README.md
./src/opendr/perception/pose_estimation/lightweight_open_pose/__init__.py
./src/opendr/perception/pose_estimation/lightweight_open_pose/filtered_pose.py
./src/opendr/perception/pose_estimation/lightweight_open_pose/lightweight_open_pose_learner.py
./src/opendr/perception/pose_estimation/lightweight_open_pose/utilities.py
./src/opendr/perception/pose_estimation/lightweight_open_pose/algorithm/README.md
./src/opendr/perception/pose_estimation/lightweight_open_pose/algorithm/__init__.py
./src/opendr/perception/pose_estimation/lightweight_open_pose/algorithm/val.py
./src/opendr/perception/pose_estimation/lightweight_open_pose/algorithm/datasets/__init__.py
./src/opendr/perception/pose_estimation/lightweight_open_pose/algorithm/datasets/coco.py
./src/opendr/perception/pose_estimation/lightweight_open_pose/algorithm/datasets/transformations.py
./src/opendr/perception/pose_estimation/lightweight_open_pose/algorithm/models/__init__.py
./src/opendr_toolkit_pose_estimation.egg-info/PKG-INFO
./src/opendr_toolkit_pose_estimation.egg-info/SOURCES.txt
./src/opendr_toolkit_pose_estimation.egg-info/dependency_links.txt
./src/opendr_toolkit_pose_estimation.egg-info/requires.txt
./src/opendr_toolkit_pose_estimation.egg-info/top_level.txt
